personalWebbingCommunication/__init__.py
personalWebbingCommunication/multipart.py
personalWebbingCommunication/test.py
personalWebbingCommunication-1.1.2.dist-info/METADATA
personalWebbingCommunication-1.1.2.dist-info/WHEEL
personalWebbingCommunication-1.1.2.dist-info/entry_points.txt
personalWebbingCommunication-1.1.2.dist-info/top_level.txt
personalWebbingCommunication-1.1.2.dist-info/RECORD
